llm_radar/__init__.py
llm_radar/aggregate_with_claude.py
llm_radar/fetch_models.py
llm_radar/mcp_server.py
llm_radar_mcp-0.1.1.dist-info/METADATA
llm_radar_mcp-0.1.1.dist-info/WHEEL
llm_radar_mcp-0.1.1.dist-info/entry_points.txt
llm_radar_mcp-0.1.1.dist-info/licenses/LICENSE
llm_radar_mcp-0.1.1.dist-info/RECORD
