Metadata-Version: 2.4
Name: llm-radar-mcp
Version: 0.1.1
Summary: MCP server providing real-time AI model intelligence - pricing, capabilities, and recommendations
Project-URL: Homepage, https://llm-radar.ajents.company
Project-URL: Repository, https://github.com/ajentsor/llm-radar
Project-URL: Documentation, https://github.com/ajentsor/llm-radar#readme
Author: ajentsor
License-Expression: MIT
License-File: LICENSE
Keywords: ai,anthropic,claude,gemini,google,llm,mcp,models,openai
Classifier: Development Status :: 4 - Beta
Classifier: Intended Audience :: Developers
Classifier: License :: OSI Approved :: MIT License
Classifier: Programming Language :: Python :: 3
Classifier: Programming Language :: Python :: 3.10
Classifier: Programming Language :: Python :: 3.11
Classifier: Programming Language :: Python :: 3.12
Requires-Python: >=3.10
Requires-Dist: anthropic>=0.40.0
Requires-Dist: httpx>=0.27.0
Requires-Dist: mcp>=1.0.0
Requires-Dist: python-dotenv>=1.0.0
Requires-Dist: starlette>=0.38.0
Requires-Dist: uvicorn>=0.30.0
Provides-Extra: dev
Requires-Dist: pytest-asyncio>=0.23.0; extra == 'dev'
Requires-Dist: pytest>=8.0.0; extra == 'dev'
